{"id":"index.js","dependencies":[{"name":"/Users/pepa/Documents/projects/react-project/package.json","includedInParent":true,"mtime":1536681829057},{"name":"react","loc":{"line":1,"column":18},"parent":"/Users/pepa/Documents/projects/react-project/src/index.js","resolved":"/Users/pepa/Documents/projects/react-project/node_modules/react/index.js"},{"name":"react-dom","loc":{"line":2,"column":21},"parent":"/Users/pepa/Documents/projects/react-project/src/index.js","resolved":"/Users/pepa/Documents/projects/react-project/node_modules/react-dom/index.js"},{"name":"./Components/Menu","loc":{"line":5,"column":17},"parent":"/Users/pepa/Documents/projects/react-project/src/index.js","resolved":"/Users/pepa/Documents/projects/react-project/src/Components/Menu.js"},{"name":"./Components/Header","loc":{"line":6,"column":19},"parent":"/Users/pepa/Documents/projects/react-project/src/index.js","resolved":"/Users/pepa/Documents/projects/react-project/src/Components/Header.js"},{"name":"./Components/Image","loc":{"line":7,"column":18},"parent":"/Users/pepa/Documents/projects/react-project/src/index.js","resolved":"/Users/pepa/Documents/projects/react-project/src/Components/Image.js"},{"name":"./routes","loc":{"line":8,"column":19},"parent":"/Users/pepa/Documents/projects/react-project/src/index.js","resolved":"/Users/pepa/Documents/projects/react-project/src/routes.js"}],"generated":{"js":"'use strict';\n\nvar _react = require('react');\n\nvar _react2 = _interopRequireDefault(_react);\n\nvar _reactDom = require('react-dom');\n\nvar _reactDom2 = _interopRequireDefault(_reactDom);\n\nvar _Menu = require('./Components/Menu');\n\nvar _Menu2 = _interopRequireDefault(_Menu);\n\nvar _Header = require('./Components/Header');\n\nvar _Header2 = _interopRequireDefault(_Header);\n\nvar _Image = require('./Components/Image');\n\nvar _Image2 = _interopRequireDefault(_Image);\n\nvar _routes = require('./routes');\n\nvar _routes2 = _interopRequireDefault(_routes);\n\nfunction _interopRequireDefault(obj) { return obj && obj.__esModule ? obj : { default: obj }; }\n\nvar App = function App() {\n  return _react2.default.createElement(\n    'div',\n    null,\n    _react2.default.createElement(_Header2.default, null),\n    _react2.default.createElement(_Menu2.default, null),\n    _react2.default.createElement(_routes2.default, null)\n  );\n};\n\n_reactDom2.default.render(_react2.default.createElement(App, null), document.getElementById('app'));","map":{"mappings":[{"generated":{"line":3,"column":0},"source":"index.js","original":{"line":1,"column":0}},{"generated":{"line":7,"column":0},"source":"index.js","original":{"line":2,"column":0}},{"generated":{"line":11,"column":0},"source":"index.js","original":{"line":5,"column":0}},{"generated":{"line":15,"column":0},"source":"index.js","original":{"line":6,"column":0}},{"generated":{"line":19,"column":0},"source":"index.js","original":{"line":7,"column":0}},{"generated":{"line":23,"column":0},"source":"index.js","original":{"line":8,"column":0}},{"generated":{"line":29,"column":0},"source":"index.js","original":{"line":11,"column":0}},{"name":"App","generated":{"line":29,"column":4},"source":"index.js","original":{"line":11,"column":6}},{"generated":{"line":29,"column":10},"source":"index.js","original":{"line":11,"column":12}},{"name":"App","generated":{"line":29,"column":19},"source":"index.js","original":{"line":11,"column":6}},{"generated":{"line":29,"column":22},"source":"index.js","original":{"line":11,"column":12}},{"generated":{"line":30,"column":0},"source":"index.js","original":{"line":11,"column":12}},{"generated":{"line":30,"column":9},"source":"index.js","original":{"line":11,"column":18}},{"generated":{"line":31,"column":0},"source":"index.js","original":{"line":11,"column":18}},{"generated":{"line":32,"column":0},"source":"index.js","original":{"line":11,"column":18}},{"generated":{"line":33,"column":0},"source":"index.js","original":{"line":11,"column":23}},{"generated":{"line":33,"column":34},"source":"index.js","original":{"line":11,"column":24}},{"generated":{"line":33,"column":50},"source":"index.js","original":{"line":11,"column":23}},{"generated":{"line":33,"column":57},"source":"index.js","original":{"line":11,"column":18}},{"generated":{"line":34,"column":0},"source":"index.js","original":{"line":11,"column":33}},{"generated":{"line":34,"column":34},"source":"index.js","original":{"line":11,"column":34}},{"generated":{"line":34,"column":48},"source":"index.js","original":{"line":11,"column":33}},{"generated":{"line":34,"column":55},"source":"index.js","original":{"line":11,"column":18}},{"generated":{"line":35,"column":0},"source":"index.js","original":{"line":11,"column":41}},{"generated":{"line":35,"column":34},"source":"index.js","original":{"line":11,"column":42}},{"generated":{"line":35,"column":50},"source":"index.js","original":{"line":11,"column":41}},{"generated":{"line":36,"column":0},"source":"index.js","original":{"line":11,"column":18}},{"generated":{"line":36,"column":3},"source":"index.js","original":{"line":11,"column":12}},{"generated":{"line":37,"column":0},"source":"index.js","original":{"line":11,"column":12}},{"generated":{"line":37,"column":1},"source":"index.js","original":{"line":11,"column":0}},{"name":"ReactDOM","generated":{"line":39,"column":0},"source":"index.js","original":{"line":13,"column":0}},{"name":"render","generated":{"line":39,"column":19},"source":"index.js","original":{"line":13,"column":9}},{"generated":{"line":39,"column":25},"source":"index.js","original":{"line":13,"column":0}},{"generated":{"line":39,"column":26},"source":"index.js","original":{"line":13,"column":16}},{"generated":{"line":39,"column":56},"source":"index.js","original":{"line":13,"column":17}},{"generated":{"line":39,"column":59},"source":"index.js","original":{"line":13,"column":16}},{"generated":{"line":39,"column":66},"source":"index.js","original":{"line":13,"column":0}},{"name":"document","generated":{"line":39,"column":68},"source":"index.js","original":{"line":13,"column":25}},{"name":"getElementById","generated":{"line":39,"column":77},"source":"index.js","original":{"line":13,"column":34}},{"generated":{"line":39,"column":91},"source":"index.js","original":{"line":13,"column":25}},{"generated":{"line":39,"column":92},"source":"index.js","original":{"line":13,"column":49}},{"generated":{"line":39,"column":97},"source":"index.js","original":{"line":13,"column":25}},{"generated":{"line":39,"column":98},"source":"index.js","original":{"line":13,"column":0}}],"sources":{"index.js":"import React from 'react';\nimport ReactDOM from 'react-dom';\n\n\nimport Menu from './Components/Menu';\nimport Header from './Components/Header';\nimport Image from './Components/Image';\nimport Routes from './routes';\n\n\nconst App = () => <div><Header /><Menu /><Routes /></div>;\n\nReactDOM.render(<App />, document.getElementById('app'));"},"lineCount":null}},"hash":"31b1af81b182f77b9ac25e255d09e05d","cacheData":{"env":{}}}